aai_engine_package/__init__.py
aai_engine_package/engine.py
aai_engine_package/engine_util.py
aai_engine_package/file_data.py
aai_engine_package/screenshot_taker.py
aai_engine_package/gui_dir/__init__.py
aai_engine_package/gui_dir/gui.py
aai_engine_package/gui_dir/pages/__init__.py
aai_engine_package/gui_dir/pages/first_run_page.py
aai_engine_package/gui_dir/pages/main_page.py
aai_engine_package/gui_dir/screenshot_taker/MessageBox_Class.py
aai_engine_package/gui_dir/screenshot_taker/OCR_screenshot_flow.py
aai_engine_package/gui_dir/screenshot_taker/__init__.py
aai_engine_package/gui_dir/screenshot_taker/normal_screenshot_flow.py
aai_engine_package/gui_dir/screenshot_taker/screenshot_taker_manager.py
aai_engine_package/gui_dir/style/__init__.py
aai_engine_package/gui_dir/style/theme.py
aai_engine_package/gui_dir/style/theme/__init__.py
aai_engine_package/gui_dir/utils/__init__.py
aai_engine_package/gui_dir/utils/capture.py
aai_engine-0.0.33.dist-info/LICENSE
aai_engine-0.0.33.dist-info/METADATA
aai_engine-0.0.33.dist-info/WHEEL
aai_engine-0.0.33.dist-info/entry_points.txt
aai_engine-0.0.33.dist-info/top_level.txt
aai_engine-0.0.33.dist-info/RECORD
