Metadata-Version: 2.1
Name: aai-engine
Version: 0.0.33
Summary: Ad Astra Industries RPA engine
Home-page: https://adastraindustries.com
Author: Toto De Brant
Author-email: toto@adastraindustries.com
Project-URL: Bug Tracker, https://adastraindustries.com
Project-URL: Documentation, https://aai-org.github.io/aai_engine_manager/
Classifier: Programming Language :: Python :: 3
Classifier: License :: OSI Approved :: MIT License
Classifier: Operating System :: OS Independent
Requires-Python: >=3.10
License-File: LICENSE
Requires-Dist: pyautogui
Requires-Dist: pillow
Requires-Dist: pandas
